pythonator_123/__init__.py
pythonator_123/amazing_function.py
pythonator_123-0.1.4.dist-info/LICENCE
pythonator_123-0.1.4.dist-info/METADATA
pythonator_123-0.1.4.dist-info/WHEEL
pythonator_123-0.1.4.dist-info/top_level.txt
pythonator_123-0.1.4.dist-info/RECORD
