Metadata-Version: 2.1
Name: pythonator-123
Version: 0.1.4
Summary: My test package for stuff with things
Author-email: Rob Campbell <git@raacampbell.com>
License: BSD 3-Clause
Requires-Python: >=3.8.0
License-File: LICENCE
Provides-Extra: dev
Requires-Dist: pytest ; extra == 'dev'
Requires-Dist: setuptools-scm ; extra == 'dev'
Requires-Dist: black ; extra == 'dev'
Requires-Dist: flake8 ; extra == 'dev'
Requires-Dist: pre-commit ; extra == 'dev'
